pyhkconnect/__init__.py
pyhkconnect/daily_statistics.py
pyhkconnect/shareholding.py
pyhkconnect/urls.py
pyhkconnect-0.0.1.dist-info/LICENSE
pyhkconnect-0.0.1.dist-info/METADATA
pyhkconnect-0.0.1.dist-info/WHEEL
pyhkconnect-0.0.1.dist-info/top_level.txt
pyhkconnect-0.0.1.dist-info/RECORD
