Metadata-Version: 2.1
Name: pyhkconnect
Version: 0.0.1
Summary: 香港交易所 沪港通 深港通 数据接口 HKC
Home-page: https://github.com/uname-yang/pyhkconnect
Author: Yang Yu
Author-email: yang.lights@hotmail.com
License: UNKNOWN
Keywords: Financial Data,HKEX,HKC,沪港通,深港通,Python Api
Platform: UNKNOWN
Classifier: Programming Language :: Python :: 3
Classifier: License :: OSI Approved :: MIT License
Classifier: Operating System :: OS Independent
Requires-Dist: pandas (>=0.18.0)
Requires-Dist: requests (>=2.0.0)
Requires-Dist: lxml (>=3.8.0)
Requires-Dist: simplejson (>=3.16.0)
Requires-Dist: beautifulsoup4 (>=4.6.3)
